langviz_studio/__init__.py
langviz_studio/observability.py
langviz_studio-0.1.2.dist-info/LICENSE
langviz_studio-0.1.2.dist-info/METADATA
langviz_studio-0.1.2.dist-info/WHEEL
langviz_studio-0.1.2.dist-info/RECORD
